scriptify/__init__.py
scriptify/scriptify.py
scriptify-0.0.1.dist-info/LICENSE
scriptify-0.0.1.dist-info/METADATA
scriptify-0.0.1.dist-info/WHEEL
scriptify-0.0.1.dist-info/top_level.txt
scriptify-0.0.1.dist-info/RECORD
